pealkoGPT/PGPT.py
pealkoGPT/__init__.py
pealkoGPT/main.py
pealkoGPT/main1.py
pealkoGPT-0.0.1.dist-info/METADATA
pealkoGPT-0.0.1.dist-info/WHEEL
pealkoGPT-0.0.1.dist-info/top_level.txt
pealkoGPT-0.0.1.dist-info/RECORD
